pydoi/__init__.py
pyDOI-0.2.1.dist-info/LICENSE
pyDOI-0.2.1.dist-info/METADATA
pyDOI-0.2.1.dist-info/WHEEL
pyDOI-0.2.1.dist-info/top_level.txt
pyDOI-0.2.1.dist-info/RECORD
