Metadata-Version: 2.1
Name: pyDOI
Version: 0.2.1
Summary: Python DOI Resolver
Home-page: https://github.com/lcnittl/pyDOI
Author: Christian Knittl-Frank
Author-email: lcnittl@gmail.com
License: GPL-3.0
Download-URL: http://pypi.python.org/pypi/pyDOI
Project-URL: GitHub: repo, https://github.com/lcnittl/pyDOI
Project-URL: GitHub: issues, https://github.com/lcnittl/pyDOI/issues
Platform: UNKNOWN
Classifier: Development Status :: 3 - Alpha
Classifier: Environment :: Console
Classifier: Intended Audience :: Developers
Classifier: License :: OSI Approved :: GNU General Public License v3 (GPLv3)
Classifier: License :: OSI Approved :: GNU General Public License v3 or later (GPLv3+)
Classifier: Operating System :: OS Independent
Classifier: Programming Language :: Python :: 3
Classifier: Programming Language :: Python :: 3 :: Only
Classifier: Programming Language :: Python :: 3.8
Classifier: Programming Language :: Python :: 3.9
Classifier: Topic :: System :: Hardware
Classifier: Topic :: Utilities
Requires-Python: >=3.8
License-File: LICENSE
Requires-Dist: requests (>=2.25.1)
